Metadata-Version: 2.1
Name: greendeck-timeseries-gen
Version: 3.0.2
Summary: Greendeck Time Series
Home-page: UNKNOWN
Author: sambal shikhar
Author-email: sambal@greendeck.com
License: UNKNOWN
Platform: UNKNOWN
Classifier: Programming Language :: Python :: 3
Classifier: License :: OSI Approved :: MIT License
Classifier: Operating System :: OS Independent
Requires-Dist: timesynth
